bc2appsource/__init__.py
bc2appsource/auth.py
bc2appsource/cli.py
bc2appsource/publisher.py
bc2appsource-1.0.0.dist-info/licenses/LICENSE
tests/__init__.py
tests/test_auth.py
tests/test_publisher.py
bc2appsource-1.0.0.dist-info/METADATA
bc2appsource-1.0.0.dist-info/WHEEL
bc2appsource-1.0.0.dist-info/entry_points.txt
bc2appsource-1.0.0.dist-info/top_level.txt
bc2appsource-1.0.0.dist-info/RECORD
