Metadata-Version: 2.4
Name: bc2appsource
Version: 1.0.0
Summary: A tool to publish Business Central apps to Microsoft AppSource
Home-page: https://github.com/attieretief/bc2appsource
Author: Attie Retief
Author-email: attie@example.com
Project-URL: Bug Reports, https://github.com/attieretief/bc2appsource/issues
Project-URL: Source, https://github.com/attieretief/bc2appsource
Project-URL: Documentation, https://github.com/attieretief/bc2appsource#readme
Keywords: business-central appsource microsoft dynamics365
Classifier: Development Status :: 4 - Beta
Classifier: Intended Audience :: Developers
Classifier: License :: OSI Approved :: MIT License
Classifier: Operating System :: OS Independent
Classifier: Programming Language :: Python :: 3
Classifier: Programming Language :: Python :: 3.8
Classifier: Programming Language :: Python :: 3.9
Classifier: Programming Language :: Python :: 3.10
Classifier: Programming Language :: Python :: 3.11
Classifier: Programming Language :: Python :: 3.12
Classifier: Topic :: Software Development :: Build Tools
Classifier: Topic :: System :: Software Distribution
Requires-Python: >=3.8
License-File: LICENSE
Requires-Dist: requests>=2.31.0
Requires-Dist: click>=8.0.0
Dynamic: author
Dynamic: author-email
Dynamic: classifier
Dynamic: description
Dynamic: description-content-type
Dynamic: home-page
Dynamic: keywords
Dynamic: license-file
Dynamic: project-url
Dynamic: requires-dist
Dynamic: requires-python
Dynamic: summary
